{
  "hash": "705d0fdd",
  "configHash": "2cd8b149",
  "lockfileHash": "06064d48",
  "browserHash": "3ee8d4d1",
  "optimized": {
    "react/jsx-dev-runtime": {
      "src": "../../node_modules/react/jsx-dev-runtime.js",
      "file": "react_jsx-dev-runtime.js",
      "fileHash": "74d9df98",
      "needsInterop": true
    },
    "react": {
      "src": "../../node_modules/react/index.js",
      "file": "react.js",
      "fileHash": "8ca10e0e",
      "needsInterop": true
    },
    "react-dom/client": {
      "src": "../../node_modules/react-dom/client.js",
      "file": "react-dom_client.js",
      "fileHash": "e5315a8f",
      "needsInterop": true
    },
    "react-router-dom": {
      "src": "../../node_modules/react-router-dom/dist/index.js",
      "file": "react-router-dom.js",
      "fileHash": "4d5f54ba",
      "needsInterop": false
    }
  },
  "chunks": {
    "chunk-UWZXFKA6": {
      "file": "chunk-UWZXFKA6.js"
    },
    "chunk-UPDK7Z2H": {
      "file": "chunk-UPDK7Z2H.js"
    }
  }
}